{
    "$schema": "http://json-schema.org/draft-04/schema#",
    "$id": "pbxadminapi.getconfigobjectsresult.schema.json",
    "type": "object",
    "properties": {
      "api": {
        "type": "string",
        "enum": [
          "PbxAdminApi"
        ]
      },
      "mt": {
        "type": "string",
        "enum": [
          "GetConfigObjectsResult"
        ]
      },
      "objects": {
        "type": "array",
        "items": {
            "type": "object",
            "properties": {
                "cn": {
                    "type": "string"
                },
                "guid": {
                    "type": "string"
                }
            },
            "required": ["cn", "config"]
        }
      }
    },
    "required": ["api", "mt", "objects"]
}